marketquery/__init__.py
marketquery/cache.py
marketquery/client.py
marketquery/constants.py
marketquery/providers/__init__.py
marketquery/providers/alpha_vantage.py
marketquery/providers/base.py
marketquery/providers/polygon.py
marketquery/providers/stooq.py
marketquery/providers/tiingo.py
marketquery/providers/yahoo.py
marketquery-0.1.0.dist-info/METADATA
marketquery-0.1.0.dist-info/WHEEL
marketquery-0.1.0.dist-info/licenses/LICENSE
marketquery-0.1.0.dist-info/RECORD
