Metadata-Version: 2.4
Name: marketquery
Version: 0.1.0
Summary: A unified interface for market data APIs
Project-URL: Homepage, https://github.com/troyscribner/marketquery
Project-URL: Documentation, https://github.com/troyscribner/marketquery#readme
Project-URL: Repository, https://github.com/troyscribner/marketquery.git
Project-URL: Issues, https://github.com/troyscribner/marketquery/issues
Author-email: Troy Scribner <your.email@example.com>
License-Expression: MIT
License-File: LICENSE
Keywords: api,data,finance,market,stocks
Classifier: Development Status :: 4 - Beta
Classifier: Intended Audience :: Financial and Insurance Industry
Classifier: License :: OSI Approved :: MIT License
Classifier: Programming Language :: Python :: 3
Classifier: Programming Language :: Python :: 3.8
Classifier: Programming Language :: Python :: 3.9
Classifier: Programming Language :: Python :: 3.10
Classifier: Programming Language :: Python :: 3.11
Classifier: Topic :: Office/Business :: Financial :: Investment
Requires-Python: >=3.8
Requires-Dist: alpha-vantage>=2.3.1
Requires-Dist: appdirs>=1.4.4
Requires-Dist: pandas>=1.3.0
Requires-Dist: polygon-api-client>=1.12.0
Requires-Dist: requests>=2.26.0
Requires-Dist: tiingo>=0.4.0
Requires-Dist: tqdm>=4.62.0
Requires-Dist: yfinance>=0.2.0
Provides-Extra: dev
Requires-Dist: black>=21.7b0; extra == 'dev'
Requires-Dist: flake8>=3.9.0; extra == 'dev'
Requires-Dist: isort>=5.9.0; extra == 'dev'
Requires-Dist: mypy>=0.910; extra == 'dev'
Requires-Dist: pytest-cov>=2.12.0; extra == 'dev'
Requires-Dist: pytest>=6.0.0; extra == 'dev'
